helloworld/__init__.py
helloworld/a.py
sayhellox123-0.6.dist-info/METADATA
sayhellox123-0.6.dist-info/WHEEL
sayhellox123-0.6.dist-info/entry_points.txt
sayhellox123-0.6.dist-info/top_level.txt
sayhellox123-0.6.dist-info/RECORD
