Metadata-Version: 2.1
Name: sayhellox123
Version: 0.6
Summary: says hello
